nips/__init__.py
nips/data_file_record.py
nips/data_set.py
nips/data_value_mode.py
nips/element_format_record.py
nips/fft.py
nips/logical_record.py
nipsext/__init__.py
nipsext/__main__.py
nipsext/info.py
nipsext/logical.py
nipsext/rec.py
nipsext/repl.py
nipsext/sqlite.py
pynips-0.2.1.dist-info/METADATA
pynips-0.2.1.dist-info/WHEEL
pynips-0.2.1.dist-info/entry_points.txt
pynips-0.2.1.dist-info/licenses/COPYING
pynips-0.2.1.dist-info/RECORD
