Metadata-Version: 2.3
Name: pynips
Version: 0.2.1
Summary: A Python library for reading data from NIPS 360 FFS data files
Project-URL: Homepage, https://codeberg.org/ctrlall/pynips
Project-URL: Bug Tracker, https://codeberg.org/ctrlall/pynips/issues
Project-URL: Documentation, https://ctrlall.codeberg.page/pynips/
Author-email: pukkamustard <pukkamustard@posteo.net>, Moritz Feichtinger <moritz.feichtinger@unibas.ch>
License: GNU AFFERO GENERAL PUBLIC LICENSE
License-File: COPYING
Classifier: Intended Audience :: Science/Research
Classifier: License :: OSI Approved :: GNU Affero General Public License v3 or later (AGPLv3+)
Classifier: Operating System :: OS Independent
Classifier: Programming Language :: Python :: 3
Classifier: Topic :: Sociology :: History
Classifier: Topic :: System :: Archiving
Requires-Python: >=3.10
Requires-Dist: ebcdic
Requires-Dist: progressbar2
